protocards/__init__.py
protocards/base.py
protocards/cribbage.py
protocards/standard.py
protocards/tests/__init__.py
protocards/tests/test_base.py
protocards/tests/test_cribbage.py
protocards/tests/test_standard.py
protocards-0.2.0.dist-info/LICENSE
protocards-0.2.0.dist-info/METADATA
protocards-0.2.0.dist-info/WHEEL
protocards-0.2.0.dist-info/top_level.txt
protocards-0.2.0.dist-info/RECORD
