Metadata-Version: 2.1
Name: protocards
Version: 0.2.0
Summary: Basic tools for working with generic game cards in python.
Home-page: https://github.com/relsqui/protocards
Author: Finn Ellis
Author-email: relsqui@chiliahedron.com
License: MIT
Classifier: Development Status :: 3 - Alpha
Classifier: Intended Audience :: Developers
Classifier: Operating System :: OS Independent
Classifier: Programming Language :: Python :: 3
Classifier: License :: OSI Approved :: MIT License
Classifier: Topic :: Software Development :: Libraries :: Python Modules
License-File: LICENSE
